{
  "next_period": "2026117",
  "based_on_period": "2026116",
  "recommendation": {
    "normal_numbers": [
      5,
      12,
      14,
      35,
      43,
      44
    ],
    "special_numbers": [
      2,
      14,
      43,
      12,
      44,
      35
    ],
    "primary_special_zodiac": "蛇"
  },
  "recommended_normal": [
    5,
    12,
    14,
    35,
    43,
    44
  ],
  "recommended_special_top5": [
    2,
    14,
    43,
    12,
    44,
    35
  ],
  "primary_special": 2,
  "primary_special_zodiac": "蛇",
  "combo_attributes": {
    "odd_even": "奇3偶4",
    "big_small": "大3小4",
    "sum": 155
  },
  "top_scores": [
    [
      2,
      32.124230319547536,
      "蛇",
      "火",
      "红"
    ],
    [
      14,
      31.79363899538592,
      "蛇",
      "水",
      "蓝"
    ],
    [
      43,
      31.711429195641998,
      "鼠",
      "金",
      "绿"
    ],
    [
      12,
      31.648311889570714,
      "羊",
      "金",
      "红"
    ],
    [
      44,
      31.403728099104477,
      "豬",
      "水",
      "绿"
    ],
    [
      35,
      31.278712422212234,
      "猴",
      "金",
      "红"
    ],
    [
      5,
      31.26571532147945,
      "虎",
      "金",
      "绿"
    ],
    [
      26,
      31.15822985132175,
      "蛇",
      "金",
      "蓝"
    ],
    [
      38,
      31.087746054251177,
      "蛇",
      "木",
      "绿"
    ],
    [
      49,
      31.08658925949191,
      "馬",
      "火",
      "绿"
    ],
    [
      47,
      31.068530327517156,
      "猴",
      "木",
      "蓝"
    ],
    [
      13,
      30.908445527145076,
      "馬",
      "金",
      "红"
    ],
    [
      32,
      30.898519394185488,
      "豬",
      "火",
      "绿"
    ],
    [
      31,
      30.736043443826013,
      "鼠",
      "水",
      "蓝"
    ],
    [
      20,
      30.700357933096367,
      "豬",
      "土",
      "蓝"
    ],
    [
      36,
      30.609840161346867,
      "羊",
      "土",
      "蓝"
    ],
    [
      19,
      30.381974674244454,
      "鼠",
      "火",
      "红"
    ],
    [
      37,
      30.352107186726524,
      "馬",
      "土",
      "蓝"
    ],
    [
      9,
      30.24841743837888,
      "狗",
      "木",
      "蓝"
    ],
    [
      45,
      30.18241444146518,
      "狗",
      "水",
      "红"
    ]
  ]
}